<?xml version="1.0" encoding="UTF-8" standalone="yes"?>
<response>
	<header>
		<resultCode>00</resultCode>
		<resultMsg>NORMAL SERVICE.</resultMsg>
	</header>
	<body>
		<items>
			<item>
				<archArea>271.63</archArea>
				<atchBldArea>0</atchBldArea>
				<atchBldCnt>0</atchBldCnt>
				<bcRat>0</bcRat>
				<bjdongCd>10300</bjdongCd>
				<bldNm>
				</bldNm>
				<block>
				</block>
				<bun>0012</bun>
				<bylotCnt>0</bylotCnt>
				<crtnDay>20171206</crtnDay>
				<dongNm>
				</dongNm>
				<emgenUseElvtCnt>0</emgenUseElvtCnt>
				<engrEpi>0</engrEpi>
				<engrGrade>
				</engrGrade>
				<engrRat>0</engrRat>
				<etcPurps>교육연구시설</etcPurps>
				<etcRoof>아스팔트슁글</etcRoof>
				<etcStrct>연와조</etcStrct>
				<fmlyCnt>0</fmlyCnt>
				<gnBldCert>0</gnBldCert>
				<gnBldGrade>
				</gnBldGrade>
				<grndFlrCnt>2</grndFlrCnt>
				<heit>0</heit>
				<hhldCnt>0</hhldCnt>
				<hoCnt>0</hoCnt>
				<indrAutoArea>0</indrAutoArea>
				<indrAutoUtcnt>0</indrAutoUtcnt>
				<indrMechArea>0</indrMechArea>
				<indrMechUtcnt>0</indrMechUtcnt>
				<itgBldCert>0</itgBldCert>
				<itgBldGrade>
				</itgBldGrade>
				<ji>0000</ji>
				<lot>
				</lot>
				<mainAtchGbCd>0</mainAtchGbCd>
				<mainAtchGbCdNm>주건축물</mainAtchGbCdNm>
				<mainPurpsCd>10000</mainPurpsCd>
				<mainPurpsCdNm>교육연구시설</mainPurpsCdNm>
				<mgmBldrgstPk>11680-7004</mgmBldrgstPk>
				<naBjdongCd>
				</naBjdongCd>
				<naMainBun>0.0</naMainBun>
				<naRoadCd>
				</naRoadCd>
				<naSubBun>0.0</naSubBun>
				<naUgrndCd>0</naUgrndCd>
				<newPlatPlc>
				</newPlatPlc>
				<oudrAutoArea>0</oudrAutoArea>
				<oudrAutoUtcnt>0</oudrAutoUtcnt>
				<oudrMechArea>0</oudrMechArea>
				<oudrMechUtcnt>0</oudrMechUtcnt>
				<platArea>0</platArea>
				<platGbCd>0</platGbCd>
				<platPlc>서울특별시 강남구 개포동 12번지</platPlc>
				<pmsDay>19891226</pmsDay>
				<pmsnoGbCd>
				</pmsnoGbCd>
				<pmsnoGbCdNm>
				</pmsnoGbCdNm>
				<pmsnoKikCd>
				</pmsnoKikCd>
				<pmsnoKikCdNm>
				</pmsnoKikCdNm>
				<pmsnoYear>
				</pmsnoYear>
				<regstrGbCd>1</regstrGbCd>
				<regstrGbCdNm>일반</regstrGbCdNm>
				<regstrKindCd>2</regstrKindCd>
				<regstrKindCdNm>일반건축물</regstrKindCdNm>
				<rideUseElvtCnt>0</rideUseElvtCnt>
				<rnum>1</rnum>
				<roofCd>90</roofCd>
				<roofCdNm>기타지붕</roofCdNm>
				<rserthqkAblty>
				</rserthqkAblty>
				<rserthqkDsgnApplyYn>
				</rserthqkDsgnApplyYn>
				<sigunguCd>11680</sigunguCd>
				<splotNm>
				</splotNm>
				<stcnsDay>
				</stcnsDay>
				<strctCd>11</strctCd>
				<strctCdNm>벽돌구조</strctCdNm>
				<totArea>536.06</totArea>
				<totDongTotArea>536.06</totDongTotArea>
				<ugrndFlrCnt>0</ugrndFlrCnt>
				<useAprDay>19911120</useAprDay>
				<vlRat>0</vlRat>
				<vlRatEstmTotArea>536.06</vlRatEstmTotArea>
			</item>
			<item>
				<archArea>243.59</archArea>
				<atchBldArea>0</atchBldArea>
				<atchBldCnt>0</atchBldCnt>
				<bcRat>0</bcRat>
				<bjdongCd>10300</bjdongCd>
				<bldNm>대한예수교장로회 한울교회</bldNm>
				<block>
				</block>
				<bun>0012</bun>
				<bylotCnt>0</bylotCnt>
				<crtnDay>20181117</crtnDay>
				<dongNm>
				</dongNm>
				<emgenUseElvtCnt>0</emgenUseElvtCnt>
				<engrEpi>0</engrEpi>
				<engrGrade>
				</engrGrade>
				<engrRat>0</engrRat>
				<etcPurps>교회시설</etcPurps>
				<etcRoof>조적조</etcRoof>
				<etcStrct>철근콘크리트조</etcStrct>
				<fmlyCnt>0</fmlyCnt>
				<gnBldCert>0</gnBldCert>
				<gnBldGrade>
				</gnBldGrade>
				<grndFlrCnt>2</grndFlrCnt>
				<heit>0</heit>
				<hhldCnt>0</hhldCnt>
				<hoCnt>0</hoCnt>
				<indrAutoArea>0</indrAutoArea>
				<indrAutoUtcnt>0</indrAutoUtcnt>
				<indrMechArea>0</indrMechArea>
				<indrMechUtcnt>0</indrMechUtcnt>
				<itgBldCert>0</itgBldCert>
				<itgBldGrade>
				</itgBldGrade>
				<ji>0000</ji>
				<lot>
				</lot>
				<mainAtchGbCd>0</mainAtchGbCd>
				<mainAtchGbCdNm>주건축물</mainAtchGbCdNm>
				<mainPurpsCd>06000</mainPurpsCd>
				<mainPurpsCdNm>종교시설</mainPurpsCdNm>
				<mgmBldrgstPk>11680-7003</mgmBldrgstPk>
				<naBjdongCd>
				</naBjdongCd>
				<naMainBun>0.0</naMainBun>
				<naRoadCd>
				</naRoadCd>
				<naSubBun>0.0</naSubBun>
				<naUgrndCd>0</naUgrndCd>
				<newPlatPlc>
				</newPlatPlc>
				<oudrAutoArea>0</oudrAutoArea>
				<oudrAutoUtcnt>0</oudrAutoUtcnt>
				<oudrMechArea>0</oudrMechArea>
				<oudrMechUtcnt>0</oudrMechUtcnt>
				<platArea>0</platArea>
				<platGbCd>0</platGbCd>
				<platPlc>서울특별시 강남구 개포동 12번지</platPlc>
				<pmsDay>
				</pmsDay>
				<pmsnoGbCd>
				</pmsnoGbCd>
				<pmsnoGbCdNm>
				</pmsnoGbCdNm>
				<pmsnoKikCd>
				</pmsnoKikCd>
				<pmsnoKikCdNm>
				</pmsnoKikCdNm>
				<pmsnoYear>
				</pmsnoYear>
				<regstrGbCd>1</regstrGbCd>
				<regstrGbCdNm>일반</regstrGbCdNm>
				<regstrKindCd>2</regstrKindCd>
				<regstrKindCdNm>일반건축물</regstrKindCdNm>
				<rideUseElvtCnt>0</rideUseElvtCnt>
				<rnum>2</rnum>
				<roofCd>90</roofCd>
				<roofCdNm>기타지붕</roofCdNm>
				<rserthqkAblty>
				</rserthqkAblty>
				<rserthqkDsgnApplyYn>0</rserthqkDsgnApplyYn>
				<sigunguCd>11680</sigunguCd>
				<splotNm>
				</splotNm>
				<stcnsDay>
				</stcnsDay>
				<strctCd>21</strctCd>
				<strctCdNm>철근콘크리트구조</strctCdNm>
				<totArea>613.05</totArea>
				<totDongTotArea>613.05</totDongTotArea>
				<ugrndFlrCnt>1</ugrndFlrCnt>
				<useAprDay>19921014</useAprDay>
				<vlRat>0</vlRat>
				<vlRatEstmTotArea>487.18</vlRatEstmTotArea>
			</item>
			<item>
				<archArea>632.53</archArea>
				<atchBldArea>0</atchBldArea>
				<atchBldCnt>0</atchBldCnt>
				<bcRat>0</bcRat>
				<bjdongCd>10300</bjdongCd>
				<bldNm>
				</bldNm>
				<block>
				</block>
				<bun>0012</bun>
				<bylotCnt>0</bylotCnt>
				<crtnDay>20181214</crtnDay>
				<dongNm>
				</dongNm>
				<emgenUseElvtCnt>0</emgenUseElvtCnt>
				<engrEpi>0</engrEpi>
				<engrGrade>
				</engrGrade>
				<engrRat>0</engrRat>
				<etcPurps>노유자시설</etcPurps>
				<etcRoof>슬라브</etcRoof>
				<etcStrct>철근콘크리트조</etcStrct>
				<fmlyCnt>0</fmlyCnt>
				<gnBldCert>0</gnBldCert>
				<gnBldGrade>
				</gnBldGrade>
				<grndFlrCnt>3</grndFlrCnt>
				<heit>0</heit>
				<hhldCnt>0</hhldCnt>
				<hoCnt>0</hoCnt>
				<indrAutoArea>0</indrAutoArea>
				<indrAutoUtcnt>0</indrAutoUtcnt>
				<indrMechArea>0</indrMechArea>
				<indrMechUtcnt>0</indrMechUtcnt>
				<itgBldCert>0</itgBldCert>
				<itgBldGrade>
				</itgBldGrade>
				<ji>0000</ji>
				<lot>
				</lot>
				<mainAtchGbCd>0</mainAtchGbCd>
				<mainAtchGbCdNm>주건축물</mainAtchGbCdNm>
				<mainPurpsCd>11000</mainPurpsCd>
				<mainPurpsCdNm>노유자시설</mainPurpsCdNm>
				<mgmBldrgstPk>11680-7005</mgmBldrgstPk>
				<naBjdongCd>10301</naBjdongCd>
				<naMainBun>5.0</naMainBun>
				<naRoadCd>116804166040</naRoadCd>
				<naSubBun>0.0</naSubBun>
				<naUgrndCd>0</naUgrndCd>
				<newPlatPlc> 서울특별시 강남구 개포로109길 5</newPlatPlc>
				<oudrAutoArea>0</oudrAutoArea>
				<oudrAutoUtcnt>0</oudrAutoUtcnt>
				<oudrMechArea>0</oudrMechArea>
				<oudrMechUtcnt>0</oudrMechUtcnt>
				<platArea>0</platArea>
				<platGbCd>0</platGbCd>
				<platPlc>서울특별시 강남구 개포동 12번지</platPlc>
				<pmsDay>19891226</pmsDay>
				<pmsnoGbCd>
				</pmsnoGbCd>
				<pmsnoGbCdNm>
				</pmsnoGbCdNm>
				<pmsnoKikCd>
				</pmsnoKikCd>
				<pmsnoKikCdNm>
				</pmsnoKikCdNm>
				<pmsnoYear>
				</pmsnoYear>
				<regstrGbCd>1</regstrGbCd>
				<regstrGbCdNm>일반</regstrGbCdNm>
				<regstrKindCd>2</regstrKindCd>
				<regstrKindCdNm>일반건축물</regstrKindCdNm>
				<rideUseElvtCnt>0</rideUseElvtCnt>
				<rnum>3</rnum>
				<roofCd>10</roofCd>
				<roofCdNm>(철근)콘크리트</roofCdNm>
				<rserthqkAblty>
				</rserthqkAblty>
				<rserthqkDsgnApplyYn>0</rserthqkDsgnApplyYn>
				<sigunguCd>11680</sigunguCd>
				<splotNm>
				</splotNm>
				<stcnsDay>
				</stcnsDay>
				<strctCd>21</strctCd>
				<strctCdNm>철근콘크리트구조</strctCdNm>
				<totArea>2131.66</totArea>
				<totDongTotArea>2131.66</totDongTotArea>
				<ugrndFlrCnt>1</ugrndFlrCnt>
				<useAprDay>19911120</useAprDay>
				<vlRat>0</vlRat>
				<vlRatEstmTotArea>1853.77</vlRatEstmTotArea>
			</item>
			<item>
				<archArea>21.42</archArea>
				<atchBldArea>0</atchBldArea>
				<atchBldCnt>0</atchBldCnt>
				<bcRat>0</bcRat>
				<bjdongCd>10300</bjdongCd>
				<bldNm>대치단지</bldNm>
				<block>
				</block>
				<bun>0012</bun>
				<bylotCnt>0</bylotCnt>
				<crtnDay>20190109</crtnDay>
				<dongNm>통합경비실-3</dongNm>
				<emgenUseElvtCnt>0</emgenUseElvtCnt>
				<engrEpi>0</engrEpi>
				<engrGrade>
				</engrGrade>
				<engrRat>0</engrRat>
				<etcPurps>통합경비실</etcPurps>
				<etcRoof>(철근)콘크리트</etcRoof>
				<etcStrct>철근콘크리트구조</etcStrct>
				<fmlyCnt>0</fmlyCnt>
				<gnBldCert>0</gnBldCert>
				<gnBldGrade>
				</gnBldGrade>
				<grndFlrCnt>1</grndFlrCnt>
				<heit>3</heit>
				<hhldCnt>0</hhldCnt>
				<hoCnt>0</hoCnt>
				<indrAutoArea>0</indrAutoArea>
				<indrAutoUtcnt>0</indrAutoUtcnt>
				<indrMechArea>0</indrMechArea>
				<indrMechUtcnt>0</indrMechUtcnt>
				<itgBldCert>0</itgBldCert>
				<itgBldGrade>
				</itgBldGrade>
				<ji>0000</ji>
				<lot>
				</lot>
				<mainAtchGbCd>1</mainAtchGbCd>
				<mainAtchGbCdNm>부속건축물</mainAtchGbCdNm>
				<mainPurpsCd>02000</mainPurpsCd>
				<mainPurpsCdNm>공동주택</mainPurpsCdNm>
				<mgmBldrgstPk>11680-100207250</mgmBldrgstPk>
				<naBjdongCd>
				</naBjdongCd>
				<naMainBun>0.0</naMainBun>
				<naRoadCd>
				</naRoadCd>
				<naSubBun>0.0</naSubBun>
				<naUgrndCd>0</naUgrndCd>
				<newPlatPlc>
				</newPlatPlc>
				<oudrAutoArea>0</oudrAutoArea>
				<oudrAutoUtcnt>0</oudrAutoUtcnt>
				<oudrMechArea>0</oudrMechArea>
				<oudrMechUtcnt>0</oudrMechUtcnt>
				<platArea>0</platArea>
				<platGbCd>0</platGbCd>
				<platPlc>서울특별시 강남구 개포동 12번지</platPlc>
				<pmsDay>20100530</pmsDay>
				<pmsnoGbCd>2222</pmsnoGbCd>
				<pmsnoGbCdNm>행위허가(증축)</pmsnoGbCdNm>
				<pmsnoKikCd>3220086</pmsnoKikCd>
				<pmsnoKikCdNm>주택과</pmsnoKikCdNm>
				<pmsnoYear>2010</pmsnoYear>
				<regstrGbCd>2</regstrGbCd>
				<regstrGbCdNm>집합</regstrGbCdNm>
				<regstrKindCd>3</regstrKindCd>
				<regstrKindCdNm>표제부</regstrKindCdNm>
				<rideUseElvtCnt>0</rideUseElvtCnt>
				<rnum>4</rnum>
				<roofCd>10</roofCd>
				<roofCdNm>(철근)콘크리트</roofCdNm>
				<rserthqkAblty>
				</rserthqkAblty>
				<rserthqkDsgnApplyYn>0</rserthqkDsgnApplyYn>
				<sigunguCd>11680</sigunguCd>
				<splotNm>
				</splotNm>
				<stcnsDay>
				</stcnsDay>
				<strctCd>21</strctCd>
				<strctCdNm>철근콘크리트구조</strctCdNm>
				<totArea>21.42</totArea>
				<totDongTotArea>21.42</totDongTotArea>
				<ugrndFlrCnt>0</ugrndFlrCnt>
				<useAprDay>20110902</useAprDay>
				<vlRat>0</vlRat>
				<vlRatEstmTotArea>21.42</vlRatEstmTotArea>
			</item>
			<item>
				<archArea>609.56</archArea>
				<atchBldArea>0</atchBldArea>
				<atchBldCnt>0</atchBldCnt>
				<bcRat>0</bcRat>
				<bjdongCd>10300</bjdongCd>
				<bldNm>대치아파트106동</bldNm>
				<block>
				</block>
				<bun>0012</bun>
				<bylotCnt>0</bylotCnt>
				<crtnDay>20190530</crtnDay>
				<dongNm>106</dongNm>
				<emgenUseElvtCnt>0</emgenUseElvtCnt>
				<engrEpi>0</engrEpi>
				<engrGrade>
				</engrGrade>
				<engrRat>0</engrRat>
				<etcPurps>아파트</etcPurps>
				<etcRoof>슬라브</etcRoof>
				<etcStrct>철근콘크리트조</etcStrct>
				<fmlyCnt>0</fmlyCnt>
				<gnBldCert>0</gnBldCert>
				<gnBldGrade>
				</gnBldGrade>
				<grndFlrCnt>15</grndFlrCnt>
				<heit>0</heit>
				<hhldCnt>263</hhldCnt>
				<hoCnt>0</hoCnt>
				<indrAutoArea>0</indrAutoArea>
				<indrAutoUtcnt>0</indrAutoUtcnt>
				<indrMechArea>0</indrMechArea>
				<indrMechUtcnt>0</indrMechUtcnt>
				<itgBldCert>0</itgBldCert>
				<itgBldGrade>
				</itgBldGrade>
				<ji>0000</ji>
				<lot>
				</lot>
				<mainAtchGbCd>0</mainAtchGbCd>
				<mainAtchGbCdNm>주건축물</mainAtchGbCdNm>
				<mainPurpsCd>02000</mainPurpsCd>
				<mainPurpsCdNm>공동주택</mainPurpsCdNm>
				<mgmBldrgstPk>11680-924</mgmBldrgstPk>
				<naBjdongCd>10301</naBjdongCd>
				<naMainBun>5.0</naMainBun>
				<naRoadCd>116804166040</naRoadCd>
				<naSubBun>0.0</naSubBun>
				<naUgrndCd>0</naUgrndCd>
				<newPlatPlc> 서울특별시 강남구 개포로109길 5</newPlatPlc>
				<oudrAutoArea>0</oudrAutoArea>
				<oudrAutoUtcnt>0</oudrAutoUtcnt>
				<oudrMechArea>0</oudrMechArea>
				<oudrMechUtcnt>0</oudrMechUtcnt>
				<platArea>0</platArea>
				<platGbCd>0</platGbCd>
				<platPlc>서울특별시 강남구 개포동 12번지</platPlc>
				<pmsDay>19891226</pmsDay>
				<pmsnoGbCd>
				</pmsnoGbCd>
				<pmsnoGbCdNm>
				</pmsnoGbCdNm>
				<pmsnoKikCd>
				</pmsnoKikCd>
				<pmsnoKikCdNm>
				</pmsnoKikCdNm>
				<pmsnoYear>
				</pmsnoYear>
				<regstrGbCd>2</regstrGbCd>
				<regstrGbCdNm>집합</regstrGbCdNm>
				<regstrKindCd>3</regstrKindCd>
				<regstrKindCdNm>표제부</regstrKindCdNm>
				<rideUseElvtCnt>0</rideUseElvtCnt>
				<rnum>5</rnum>
				<roofCd>10</roofCd>
				<roofCdNm>(철근)콘크리트</roofCdNm>
				<rserthqkAblty>
				</rserthqkAblty>
				<rserthqkDsgnApplyYn>1</rserthqkDsgnApplyYn>
				<sigunguCd>11680</sigunguCd>
				<splotNm>
				</splotNm>
				<stcnsDay>
				</stcnsDay>
				<strctCd>21</strctCd>
				<strctCdNm>철근콘크리트구조</strctCdNm>
				<totArea>9572.66</totArea>
				<totDongTotArea>9572.66</totDongTotArea>
				<ugrndFlrCnt>1</ugrndFlrCnt>
				<useAprDay>19911120</useAprDay>
				<vlRat>0</vlRat>
				<vlRatEstmTotArea>9022.28</vlRatEstmTotArea>
			</item>
			<item>
				<archArea>582.39</archArea>
				<atchBldArea>0</atchBldArea>
				<atchBldCnt>0</atchBldCnt>
				<bcRat>15.96</bcRat>
				<bjdongCd>10300</bjdongCd>
				<bldNm>대청아파트301동</bldNm>
				<block>
				</block>
				<bun>0012</bun>
				<bylotCnt>0</bylotCnt>
				<crtnDay>20190530</crtnDay>
				<dongNm>301</dongNm>
				<emgenUseElvtCnt>0</emgenUseElvtCnt>
				<engrEpi>0</engrEpi>
				<engrGrade>
				</engrGrade>
				<engrRat>0</engrRat>
				<etcPurps>아파트</etcPurps>
				<etcRoof>슬라브</etcRoof>
				<etcStrct>철근콘크리트구조</etcStrct>
				<fmlyCnt>0</fmlyCnt>
				<gnBldCert>0</gnBldCert>
				<gnBldGrade>
				</gnBldGrade>
				<grndFlrCnt>15</grndFlrCnt>
				<heit>0</heit>
				<hhldCnt>161</hhldCnt>
				<hoCnt>0</hoCnt>
				<indrAutoArea>0</indrAutoArea>
				<indrAutoUtcnt>0</indrAutoUtcnt>
				<indrMechArea>0</indrMechArea>
				<indrMechUtcnt>0</indrMechUtcnt>
				<itgBldCert>0</itgBldCert>
				<itgBldGrade>
				</itgBldGrade>
				<ji>0000</ji>
				<lot>
				</lot>
				<mainAtchGbCd>0</mainAtchGbCd>
				<mainAtchGbCdNm>주건축물</mainAtchGbCdNm>
				<mainPurpsCd>02000</mainPurpsCd>
				<mainPurpsCdNm>공동주택</mainPurpsCdNm>
				<mgmBldrgstPk>11680-928</mgmBldrgstPk>
				<naBjdongCd>10301</naBjdongCd>
				<naMainBun>21.0</naMainBun>
				<naRoadCd>116804166040</naRoadCd>
				<naSubBun>0.0</naSubBun>
				<naUgrndCd>0</naUgrndCd>
				<newPlatPlc> 서울특별시 강남구 개포로109길 21</newPlatPlc>
				<oudrAutoArea>0</oudrAutoArea>
				<oudrAutoUtcnt>0</oudrAutoUtcnt>
				<oudrMechArea>0</oudrMechArea>
				<oudrMechUtcnt>0</oudrMechUtcnt>
				<platArea>0</platArea>
				<platGbCd>0</platGbCd>
				<platPlc>서울특별시 강남구 개포동 12번지</platPlc>
				<pmsDay>19900818</pmsDay>
				<pmsnoGbCd>
				</pmsnoGbCd>
				<pmsnoGbCdNm>
				</pmsnoGbCdNm>
				<pmsnoKikCd>
				</pmsnoKikCd>
				<pmsnoKikCdNm>
				</pmsnoKikCdNm>
				<pmsnoYear>
				</pmsnoYear>
				<regstrGbCd>2</regstrGbCd>
				<regstrGbCdNm>집합</regstrGbCdNm>
				<regstrKindCd>3</regstrKindCd>
				<regstrKindCdNm>표제부</regstrKindCdNm>
				<rideUseElvtCnt>0</rideUseElvtCnt>
				<rnum>6</rnum>
				<roofCd>10</roofCd>
				<roofCdNm>(철근)콘크리트</roofCdNm>
				<rserthqkAblty>
				</rserthqkAblty>
				<rserthqkDsgnApplyYn>1</rserthqkDsgnApplyYn>
				<sigunguCd>11680</sigunguCd>
				<splotNm>
				</splotNm>
				<stcnsDay>
				</stcnsDay>
				<strctCd>21</strctCd>
				<strctCdNm>철근콘크리트구조</strctCdNm>
				<totArea>8778.66</totArea>
				<totDongTotArea>8778.66</totDongTotArea>
				<ugrndFlrCnt>1</ugrndFlrCnt>
				<useAprDay>19921014</useAprDay>
				<vlRat>201.85</vlRat>
				<vlRatEstmTotArea>8424.19</vlRatEstmTotArea>
			</item>
			<item>
				<archArea>417.43</archArea>
				<atchBldArea>0</atchBldArea>
				<atchBldCnt>0</atchBldCnt>
				<bcRat>14.86</bcRat>
				<bjdongCd>10300</bjdongCd>
				<bldNm>대치아파트212동</bldNm>
				<block>
				</block>
				<bun>0012</bun>
				<bylotCnt>0</bylotCnt>
				<crtnDay>20190530</crtnDay>
				<dongNm>212</dongNm>
				<emgenUseElvtCnt>0</emgenUseElvtCnt>
				<engrEpi>0</engrEpi>
				<engrGrade>
				</engrGrade>
				<engrRat>0</engrRat>
				<etcPurps>아파트</etcPurps>
				<etcRoof>슬라브</etcRoof>
				<etcStrct>철근콘크리트조</etcStrct>
				<fmlyCnt>0</fmlyCnt>
				<gnBldCert>0</gnBldCert>
				<gnBldGrade>
				</gnBldGrade>
				<grndFlrCnt>15</grndFlrCnt>
				<heit>0</heit>
				<hhldCnt>119</hhldCnt>
				<hoCnt>0</hoCnt>
				<indrAutoArea>0</indrAutoArea>
				<indrAutoUtcnt>0</indrAutoUtcnt>
				<indrMechArea>0</indrMechArea>
				<indrMechUtcnt>0</indrMechUtcnt>
				<itgBldCert>0</itgBldCert>
				<itgBldGrade>
				</itgBldGrade>
				<ji>0000</ji>
				<lot>
				</lot>
				<mainAtchGbCd>0</mainAtchGbCd>
				<mainAtchGbCdNm>주건축물</mainAtchGbCdNm>
				<mainPurpsCd>02000</mainPurpsCd>
				<mainPurpsCdNm>공동주택</mainPurpsCdNm>
				<mgmBldrgstPk>11680-929</mgmBldrgstPk>
				<naBjdongCd>10301</naBjdongCd>
				<naMainBun>9.0</naMainBun>
				<naRoadCd>116804166040</naRoadCd>
				<naSubBun>0.0</naSubBun>
				<naUgrndCd>0</naUgrndCd>
				<newPlatPlc> 서울특별시 강남구 개포로109길 9</newPlatPlc>
				<oudrAutoArea>0</oudrAutoArea>
				<oudrAutoUtcnt>0</oudrAutoUtcnt>
				<oudrMechArea>0</oudrMechArea>
				<oudrMechUtcnt>0</oudrMechUtcnt>
				<platArea>0</platArea>
				<platGbCd>0</platGbCd>
				<platPlc>서울특별시 강남구 개포동 12번지</platPlc>
				<pmsDay>19900818</pmsDay>
				<pmsnoGbCd>
				</pmsnoGbCd>
				<pmsnoGbCdNm>
				</pmsnoGbCdNm>
				<pmsnoKikCd>
				</pmsnoKikCd>
				<pmsnoKikCdNm>
				</pmsnoKikCdNm>
				<pmsnoYear>
				</pmsnoYear>
				<regstrGbCd>2</regstrGbCd>
				<regstrGbCdNm>집합</regstrGbCdNm>
				<regstrKindCd>3</regstrKindCd>
				<regstrKindCdNm>표제부</regstrKindCdNm>
				<rideUseElvtCnt>0</rideUseElvtCnt>
				<rnum>7</rnum>
				<roofCd>10</roofCd>
				<roofCdNm>(철근)콘크리트</roofCdNm>
				<rserthqkAblty>
				</rserthqkAblty>
				<rserthqkDsgnApplyYn>1</rserthqkDsgnApplyYn>
				<sigunguCd>11680</sigunguCd>
				<splotNm>
				</splotNm>
				<stcnsDay>
				</stcnsDay>
				<strctCd>21</strctCd>
				<strctCdNm>철근콘크리트구조</strctCdNm>
				<totArea>6458.47</totArea>
				<totDongTotArea>6458.47</totDongTotArea>
				<ugrndFlrCnt>1</ugrndFlrCnt>
				<useAprDay>19921014</useAprDay>
				<vlRat>174.87</vlRat>
				<vlRatEstmTotArea>6261.45</vlRatEstmTotArea>
			</item>
			<item>
				<archArea>417.43</archArea>
				<atchBldArea>0</atchBldArea>
				<atchBldCnt>0</atchBldCnt>
				<bcRat>17.86</bcRat>
				<bjdongCd>10300</bjdongCd>
				<bldNm>대치아파트210동</bldNm>
				<block>
				</block>
				<bun>0012</bun>
				<bylotCnt>0</bylotCnt>
				<crtnDay>20190530</crtnDay>
				<dongNm>210</dongNm>
				<emgenUseElvtCnt>0</emgenUseElvtCnt>
				<engrEpi>0</engrEpi>
				<engrGrade>
				</engrGrade>
				<engrRat>0</engrRat>
				<etcPurps>아파트</etcPurps>
				<etcRoof>슬라브</etcRoof>
				<etcStrct>철근콘크리트조</etcStrct>
				<fmlyCnt>0</fmlyCnt>
				<gnBldCert>0</gnBldCert>
				<gnBldGrade>
				</gnBldGrade>
				<grndFlrCnt>15</grndFlrCnt>
				<heit>0</heit>
				<hhldCnt>119</hhldCnt>
				<hoCnt>0</hoCnt>
				<indrAutoArea>0</indrAutoArea>
				<indrAutoUtcnt>0</indrAutoUtcnt>
				<indrMechArea>0</indrMechArea>
				<indrMechUtcnt>0</indrMechUtcnt>
				<itgBldCert>0</itgBldCert>
				<itgBldGrade>
				</itgBldGrade>
				<ji>0000</ji>
				<lot>
				</lot>
				<mainAtchGbCd>0</mainAtchGbCd>
				<mainAtchGbCdNm>주건축물</mainAtchGbCdNm>
				<mainPurpsCd>02000</mainPurpsCd>
				<mainPurpsCdNm>공동주택</mainPurpsCdNm>
				<mgmBldrgstPk>11680-921</mgmBldrgstPk>
				<naBjdongCd>10301</naBjdongCd>
				<naMainBun>9.0</naMainBun>
				<naRoadCd>116804166040</naRoadCd>
				<naSubBun>0.0</naSubBun>
				<naUgrndCd>0</naUgrndCd>
				<newPlatPlc> 서울특별시 강남구 개포로109길 9</newPlatPlc>
				<oudrAutoArea>0</oudrAutoArea>
				<oudrAutoUtcnt>0</oudrAutoUtcnt>
				<oudrMechArea>0</oudrMechArea>
				<oudrMechUtcnt>0</oudrMechUtcnt>
				<platArea>0</platArea>
				<platGbCd>0</platGbCd>
				<platPlc>서울특별시 강남구 개포동 12번지</platPlc>
				<pmsDay>19900818</pmsDay>
				<pmsnoGbCd>
				</pmsnoGbCd>
				<pmsnoGbCdNm>
				</pmsnoGbCdNm>
				<pmsnoKikCd>
				</pmsnoKikCd>
				<pmsnoKikCdNm>
				</pmsnoKikCdNm>
				<pmsnoYear>
				</pmsnoYear>
				<regstrGbCd>2</regstrGbCd>
				<regstrGbCdNm>집합</regstrGbCdNm>
				<regstrKindCd>3</regstrKindCd>
				<regstrKindCdNm>표제부</regstrKindCdNm>
				<rideUseElvtCnt>0</rideUseElvtCnt>
				<rnum>8</rnum>
				<roofCd>10</roofCd>
				<roofCdNm>(철근)콘크리트</roofCdNm>
				<rserthqkAblty>
				</rserthqkAblty>
				<rserthqkDsgnApplyYn>1</rserthqkDsgnApplyYn>
				<sigunguCd>11680</sigunguCd>
				<splotNm>
				</splotNm>
				<stcnsDay>
				</stcnsDay>
				<strctCd>21</strctCd>
				<strctCdNm>철근콘크리트구조</strctCdNm>
				<totArea>6458.47</totArea>
				<totDongTotArea>6458.47</totDongTotArea>
				<ugrndFlrCnt>1</ugrndFlrCnt>
				<useAprDay>19921014</useAprDay>
				<vlRat>174.87</vlRat>
				<vlRatEstmTotArea>6261.45</vlRatEstmTotArea>
			</item>
			<item>
				<archArea>592.93</archArea>
				<atchBldArea>0</atchBldArea>
				<atchBldCnt>0</atchBldCnt>
				<bcRat>15.96</bcRat>
				<bjdongCd>10300</bjdongCd>
				<bldNm>대청아파트303동</bldNm>
				<block>
				</block>
				<bun>0012</bun>
				<bylotCnt>0</bylotCnt>
				<crtnDay>20190530</crtnDay>
				<dongNm>303</dongNm>
				<emgenUseElvtCnt>0</emgenUseElvtCnt>
				<engrEpi>0</engrEpi>
				<engrGrade>
				</engrGrade>
				<engrRat>0</engrRat>
				<etcPurps>아파트</etcPurps>
				<etcRoof>슬라브</etcRoof>
				<etcStrct>철근콘크리트조</etcStrct>
				<fmlyCnt>0</fmlyCnt>
				<gnBldCert>0</gnBldCert>
				<gnBldGrade>
				</gnBldGrade>
				<grndFlrCnt>15</grndFlrCnt>
				<heit>0</heit>
				<hhldCnt>131</hhldCnt>
				<hoCnt>0</hoCnt>
				<indrAutoArea>0</indrAutoArea>
				<indrAutoUtcnt>0</indrAutoUtcnt>
				<indrMechArea>0</indrMechArea>
				<indrMechUtcnt>0</indrMechUtcnt>
				<itgBldCert>0</itgBldCert>
				<itgBldGrade>
				</itgBldGrade>
				<ji>0000</ji>
				<lot>
				</lot>
				<mainAtchGbCd>0</mainAtchGbCd>
				<mainAtchGbCdNm>주건축물</mainAtchGbCdNm>
				<mainPurpsCd>02000</mainPurpsCd>
				<mainPurpsCdNm>공동주택</mainPurpsCdNm>
				<mgmBldrgstPk>11680-935</mgmBldrgstPk>
				<naBjdongCd>10301</naBjdongCd>
				<naMainBun>21.0</naMainBun>
				<naRoadCd>116804166040</naRoadCd>
				<naSubBun>0.0</naSubBun>
				<naUgrndCd>0</naUgrndCd>
				<newPlatPlc> 서울특별시 강남구 개포로109길 21</newPlatPlc>
				<oudrAutoArea>0</oudrAutoArea>
				<oudrAutoUtcnt>0</oudrAutoUtcnt>
				<oudrMechArea>0</oudrMechArea>
				<oudrMechUtcnt>0</oudrMechUtcnt>
				<platArea>0</platArea>
				<platGbCd>0</platGbCd>
				<platPlc>서울특별시 강남구 개포동 12번지</platPlc>
				<pmsDay>19900818</pmsDay>
				<pmsnoGbCd>
				</pmsnoGbCd>
				<pmsnoGbCdNm>
				</pmsnoGbCdNm>
				<pmsnoKikCd>
				</pmsnoKikCd>
				<pmsnoKikCdNm>
				</pmsnoKikCdNm>
				<pmsnoYear>
				</pmsnoYear>
				<regstrGbCd>2</regstrGbCd>
				<regstrGbCdNm>집합</regstrGbCdNm>
				<regstrKindCd>3</regstrKindCd>
				<regstrKindCdNm>표제부</regstrKindCdNm>
				<rideUseElvtCnt>0</rideUseElvtCnt>
				<rnum>9</rnum>
				<roofCd>10</roofCd>
				<roofCdNm>(철근)콘크리트</roofCdNm>
				<rserthqkAblty>
				</rserthqkAblty>
				<rserthqkDsgnApplyYn>1</rserthqkDsgnApplyYn>
				<sigunguCd>11680</sigunguCd>
				<splotNm>
				</splotNm>
				<stcnsDay>
				</stcnsDay>
				<strctCd>21</strctCd>
				<strctCdNm>철근콘크리트구조</strctCdNm>
				<totArea>8919.27</totArea>
				<totDongTotArea>8919.27</totDongTotArea>
				<ugrndFlrCnt>1</ugrndFlrCnt>
				<useAprDay>19921014</useAprDay>
				<vlRat>201.85</vlRat>
				<vlRatEstmTotArea>8502.65</vlRatEstmTotArea>
			</item>
			<item>
				<archArea>610.06</archArea>
				<atchBldArea>0</atchBldArea>
				<atchBldCnt>0</atchBldCnt>
				<bcRat>0</bcRat>
				<bjdongCd>10300</bjdongCd>
				<bldNm>대청아파트306동</bldNm>
				<block>
				</block>
				<bun>0012</bun>
				<bylotCnt>0</bylotCnt>
				<crtnDay>20190530</crtnDay>
				<dongNm>306</dongNm>
				<emgenUseElvtCnt>0</emgenUseElvtCnt>
				<engrEpi>0</engrEpi>
				<engrGrade>
				</engrGrade>
				<engrRat>0</engrRat>
				<etcPurps>아파트</etcPurps>
				<etcRoof>슬라브</etcRoof>
				<etcStrct>철근콘크리트조</etcStrct>
				<fmlyCnt>0</fmlyCnt>
				<gnBldCert>0</gnBldCert>
				<gnBldGrade>
				</gnBldGrade>
				<grndFlrCnt>15</grndFlrCnt>
				<heit>0</heit>
				<hhldCnt>119</hhldCnt>
				<hoCnt>0</hoCnt>
				<indrAutoArea>0</indrAutoArea>
				<indrAutoUtcnt>0</indrAutoUtcnt>
				<indrMechArea>0</indrMechArea>
				<indrMechUtcnt>0</indrMechUtcnt>
				<itgBldCert>0</itgBldCert>
				<itgBldGrade>
				</itgBldGrade>
				<ji>0000</ji>
				<lot>
				</lot>
				<mainAtchGbCd>0</mainAtchGbCd>
				<mainAtchGbCdNm>주건축물</mainAtchGbCdNm>
				<mainPurpsCd>02000</mainPurpsCd>
				<mainPurpsCdNm>공동주택</mainPurpsCdNm>
				<mgmBldrgstPk>11680-937</mgmBldrgstPk>
				<naBjdongCd>10301</naBjdongCd>
				<naMainBun>21.0</naMainBun>
				<naRoadCd>116804166040</naRoadCd>
				<naSubBun>0.0</naSubBun>
				<naUgrndCd>0</naUgrndCd>
				<newPlatPlc> 서울특별시 강남구 개포로109길 21</newPlatPlc>
				<oudrAutoArea>0</oudrAutoArea>
				<oudrAutoUtcnt>0</oudrAutoUtcnt>
				<oudrMechArea>0</oudrMechArea>
				<oudrMechUtcnt>0</oudrMechUtcnt>
				<platArea>0</platArea>
				<platGbCd>0</platGbCd>
				<platPlc>서울특별시 강남구 개포동 12번지</platPlc>
				<pmsDay>19900818</pmsDay>
				<pmsnoGbCd>
				</pmsnoGbCd>
				<pmsnoGbCdNm>
				</pmsnoGbCdNm>
				<pmsnoKikCd>
				</pmsnoKikCd>
				<pmsnoKikCdNm>
				</pmsnoKikCdNm>
				<pmsnoYear>
				</pmsnoYear>
				<regstrGbCd>2</regstrGbCd>
				<regstrGbCdNm>집합</regstrGbCdNm>
				<regstrKindCd>3</regstrKindCd>
				<regstrKindCdNm>표제부</regstrKindCdNm>
				<rideUseElvtCnt>0</rideUseElvtCnt>
				<rnum>10</rnum>
				<roofCd>10</roofCd>
				<roofCdNm>(철근)콘크리트</roofCdNm>
				<rserthqkAblty>
				</rserthqkAblty>
				<rserthqkDsgnApplyYn>1</rserthqkDsgnApplyYn>
				<sigunguCd>11680</sigunguCd>
				<splotNm>
				</splotNm>
				<stcnsDay>
				</stcnsDay>
				<strctCd>21</strctCd>
				<strctCdNm>철근콘크리트구조</strctCdNm>
				<totArea>9362.61</totArea>
				<totDongTotArea>9959.4</totDongTotArea>
				<ugrndFlrCnt>1</ugrndFlrCnt>
				<useAprDay>19921014</useAprDay>
				<vlRat>0</vlRat>
				<vlRatEstmTotArea>8965.12</vlRatEstmTotArea>
			</item>
		</items>
		<numOfRows>10</numOfRows>
		<pageNo>1</pageNo>
		<totalCount>34</totalCount>
	</body>
</response>
